regex/_main.py
regex/_regex.cpython-311-darwin.so
regex/__init__.py
regex/_regex_core.py
regex/tests/test_regex.py
regex-2026.1.14.dist-info/RECORD
regex-2026.1.14.dist-info/WHEEL
regex-2026.1.14.dist-info/top_level.txt
regex-2026.1.14.dist-info/METADATA
regex-2026.1.14.dist-info/licenses/LICENSE.txt
