Metadata-Version: 2.4
Name: regex
Version: 2026.1.14
Summary: Alternative regular expression module, to replace re.
Author-email: Matthew Barnett <regex@mrabarnett.plus.com>
License-Expression: Apache-2.0 AND CNRI-Python
Project-URL: Homepage, https://github.com/mrabarnett/mrab-regex
Classifier: Development Status :: 5 - Production/Stable
Classifier: Intended Audience :: Developers
Classifier: Operating System :: OS Independent
Classifier: Programming Language :: Python :: 3.9
Classifier: Programming Language :: Python :: 3.10
Classifier: Programming Language :: Python :: 3.11
Classifier: Programming Language :: Python :: 3.12
Classifier: Programming Language :: Python :: 3.13
Classifier: Programming Language :: Python :: 3.14
Classifier: Topic :: Scientific/Engineering :: Information Analysis
Classifier: Topic :: Software Development :: Libraries :: Python Modules
Classifier: Topic :: Text Processing
Classifier: Topic :: Text Processing :: General
Requires-Python: >=3.9
License-File: LICENSE.txt
Dynamic: license-file
